MoshishibieYuJiqiXuexiZhongwenbanMachunpeng/README.md
MoshishibieYuJiqiXuexiZhongwenbanMachunpeng/__init__.py
MoshishibieYuJiqiXuexiZhongwenbanMachunpeng/__main__.py
MoshishibieYuJiqiXuexiZhongwenbanMachunpeng/file.pdf
MoshishibieYuJiqiXuexiZhongwenbanMachunpeng/index.html
moshishibie_yu_jiqi_xuexi_zhongwenban_machunpeng-2024.3.2.0.dist-info/METADATA
moshishibie_yu_jiqi_xuexi_zhongwenban_machunpeng-2024.3.2.0.dist-info/WHEEL
moshishibie_yu_jiqi_xuexi_zhongwenban_machunpeng-2024.3.2.0.dist-info/entry_points.txt
moshishibie_yu_jiqi_xuexi_zhongwenban_machunpeng-2024.3.2.0.dist-info/top_level.txt
moshishibie_yu_jiqi_xuexi_zhongwenban_machunpeng-2024.3.2.0.dist-info/RECORD
